{
  "Title": "ECharts",
  "Components": [
    "ECharts"
  ],
  "Props": [
    {
      "Name": "Class",
      "Type": "String",
      "Default": "null",
      "Description": "The class applied to the outermost element of the component"
    },
    {
      "Name": "Height",
      "Type": "StringNumber",
      "Default": "",
      "Description": "Sets the height for the component."
    },
    {
      "Name": "Id",
      "Type": "String",
      "Default": "null",
      "Description": ""
    },
    {
      "Name": "Option",
      "Type": "Object",
      "Default": "",
      "Description": ""
    },
    {
      "Name": "Style",
      "Type": "String",
      "Default": "null",
      "Description": "The style applied to the outermost element of the component"
    },
    {
      "Name": "Width",
      "Type": "StringNumber",
      "Default": "",
      "Description": "Sets the width for the component."
    }
  ],
  "Contents": [],
  "Events": []
}