{
  "Title": "MImage",
  "Components": [
    "Images"
  ],
  "Props": [
    {
      "Name": "AspectRatio",
      "Type": "StringNumber",
      "Default": "",
      "Description": "计算为width/height，因此对于 1920x1080px 的图片，其值为 1.7778。 如果省略，将自动计算"
    },
    {
      "Name": "Class",
      "Type": "String",
      "Default": "null",
      "Description": "应用到组件最外层元素的class"
    },
    {
      "Name": "Contain",
      "Type": "Boolean",
      "Default": "false",
      "Description": "防止图像不合适时被裁剪"
    },
    {
      "Name": "ContentClass",
      "Type": "String",
      "Default": "null",
      "Description": ""
    },
    {
      "Name": "Dark",
      "Type": "Boolean",
      "Default": "false",
      "Description": "将暗色主题变量应用到组件。"
    },
    {
      "Name": "Gradient",
      "Type": "String",
      "Default": "null",
      "Description": ""
    },
    {
      "Name": "Height",
      "Type": "StringNumber",
      "Default": "",
      "Description": "设定组件的高度。"
    },
    {
      "Name": "Id",
      "Type": "String",
      "Default": "null",
      "Description": ""
    },
    {
      "Name": "LazySrc",
      "Type": "String",
      "Default": "",
      "Description": "在等待主映像加载时显示的内容，通常是一个小型的base64编码的缩略图。有一个轻微的模糊滤镜应用。"
    },
    {
      "Name": "Light",
      "Type": "Boolean",
      "Default": "false",
      "Description": ""
    },
    {
      "Name": "MaxHeight",
      "Type": "StringNumber",
      "Default": "",
      "Description": "设定组件的最大高度。"
    },
    {
      "Name": "MaxWidth",
      "Type": "StringNumber",
      "Default": "",
      "Description": "设定组件的最大宽度。"
    },
    {
      "Name": "MinHeight",
      "Type": "StringNumber",
      "Default": "",
      "Description": "设定组件的最小高度。"
    },
    {
      "Name": "MinWidth",
      "Type": "StringNumber",
      "Default": "",
      "Description": "设定组件的最小宽度。"
    },
    {
      "Name": "Position",
      "Type": "String",
      "Default": "null",
      "Description": ""
    },
    {
      "Name": "Src",
      "Type": "String",
      "Default": "null",
      "Description": "图像的 URL。这个属性是强制性的"
    },
    {
      "Name": "Style",
      "Type": "String",
      "Default": "null",
      "Description": "应用到组件最外层元素的style"
    },
    {
      "Name": "Width",
      "Type": "StringNumber",
      "Default": "",
      "Description": "设定组件的最小宽度。"
    }
  ],
  "Contents": [
    {
      "Name": "ChildContent",
      "Type": "RenderFragment",
      "Description": "默认插槽"
    },
    {
      "Name": "PlaceholderContent",
      "Type": "RenderFragment",
      "Description": ""
    }
  ],
  "Events": []
}